YunYuanshengJishuYuJiagouShijianNianhuoXiaohongshuFix1/README.md
YunYuanshengJishuYuJiagouShijianNianhuoXiaohongshuFix1/__init__.py
YunYuanshengJishuYuJiagouShijianNianhuoXiaohongshuFix1/__main__.py
YunYuanshengJishuYuJiagouShijianNianhuoXiaohongshuFix1/file.pdf
YunYuanshengJishuYuJiagouShijianNianhuoXiaohongshuFix1/index.html
yun_yuansheng_jishu_yu_jiagou_shijian_nianhuo_xiaohongshu_fix1-2025.3.25.0.dist-info/METADATA
yun_yuansheng_jishu_yu_jiagou_shijian_nianhuo_xiaohongshu_fix1-2025.3.25.0.dist-info/WHEEL
yun_yuansheng_jishu_yu_jiagou_shijian_nianhuo_xiaohongshu_fix1-2025.3.25.0.dist-info/entry_points.txt
yun_yuansheng_jishu_yu_jiagou_shijian_nianhuo_xiaohongshu_fix1-2025.3.25.0.dist-info/top_level.txt
yun_yuansheng_jishu_yu_jiagou_shijian_nianhuo_xiaohongshu_fix1-2025.3.25.0.dist-info/RECORD
